{
  "passengers": [
    {
      "fullname": "Steve",
      "id": 1,
      "checkedIn": true,
      "baggage": "none",
      "checkInDate": 15135125454235
    },
    {
      "fullname": "Marge",
      "id": 2,
      "checkedIn": true,
      "baggage": "none",
      "checkInDate": 15135125454235
    },
    {
      "fullname": "Arber",
      "id": 3,
      "checkedIn": true,
      "baggage": "none",
      "checkInDate": 15135125454235
    },
    {
      "id": 4,
      "fullname": "Renald",
      "checkedIn": false,
      "checkInDate": null,
      "baggage": ""
    },
    {
      "id": 5,
      "fullname": "Fabjola",
      "checkedIn": true,
      "checkInDate": 15135125454235,
      "baggage": ""
    }
  ]
}